evoml_client/__init__.py
evoml_client/analyser.py
evoml_client/dataset.py
evoml_client/model.py
evoml_client/models.py
evoml_client/pipeline.py
evoml_client/trial.py
evoml_client/trial_conf_detection_types.py
evoml_client/trial_conf_models.py
evoml_client/trial_config.py
evoml_client/utils.py
evoml_client/api_calls/__init__.py
evoml_client/api_calls/black_widow.py
evoml_client/api_calls/datasets.py
evoml_client/api_calls/hulk.py
evoml_client/api_calls/loki.py
evoml_client/api_calls/models.py
evoml_client/api_calls/trials.py
evoml_client/api_calls/utils.py
evoml_client/conf/__init__.py
evoml_client/conf/base_default_conf.py
evoml_client/conf/client_conf.py
evoml_client/conf/conf_manager.py
evoml_client/conf/environment_conf.py
service/__init__.py
service/helpers/__init__.py
service/helpers/environment_mgr.py
service/helpers/pipeline_mgr.py
turintech_evoml_client-1.6.1.dist-info/AUTHORS.md
turintech_evoml_client-1.6.1.dist-info/LICENSE
turintech_evoml_client-1.6.1.dist-info/METADATA
turintech_evoml_client-1.6.1.dist-info/WHEEL
turintech_evoml_client-1.6.1.dist-info/top_level.txt
turintech_evoml_client-1.6.1.dist-info/RECORD
