Metadata-Version: 2.1
Name: turintech-evoml-client
Version: 1.6.1
Summary: Python client library for core functionality of evoml
Home-page: https://turintech.ai
Author: Turing Intelligence Technology
Author-email: support@turintech.ai
License: TURING INTELLIGENCE TECHNOLOGY LIMITED END-USER LICENCE
Keywords: evoml-client
Platform: UNKNOWN
Classifier: Development Status :: 5 - Production/Stable
Classifier: License :: Other/Proprietary License
Classifier: Programming Language :: Python :: 3.9
Classifier: Programming Language :: Python :: 3.10
Requires-Python: >=3.9
License-File: LICENSE
License-File: AUTHORS.md
Requires-Dist: pandas<2.0.0,>=1.4.2
Requires-Dist: numpy<2.0.0,>=1.21.5
Requires-Dist: requests>=2.27.0
Requires-Dist: tqdm>=4.62.3
Requires-Dist: joblib<2.0.0,>=1.1.0
Requires-Dist: pydantic<2.0.0,>=1.9.1
Requires-Dist: pydantic[dotenv]<2.0.0,>=1.0.0
Requires-Dist: scikit-learn<2.0.0,>=1.1.2
Requires-Dist: pyarrow>=8.0.0
Requires-Dist: turintech-pagination==1.2.2
Requires-Dist: turintech-rest-clients==1.2.2
Requires-Dist: turintech-data-types==1.2.3
Requires-Dist: turintech-evoml-rocket-client==1.2.1rc0
Provides-Extra: full
Requires-Dist: turintech-evoml-python-dependencies[external_runtime]==2.6.0; extra == "full"
Requires-Dist: numpy<1.25.0; extra == "full"
Requires-Dist: pydantic[dotenv]<2.0.0; extra == "full"
